roc/__init__.py
roc/film/__init__.py
roc/film/commands.py
roc/film/config/__init__.py
roc/film/constants.py
roc/film/descriptor.json
roc/film/exceptions.py
roc/film/tasks/__init__.py
roc/film/tasks/cat_solo_hk.py
roc/film/tasks/cdf_postpro.py
roc/film/tasks/check_dds.py
roc/film/tasks/db_to_anc_bia_sweep_table.py
roc/film/tasks/dds_to_l0.py
roc/film/tasks/export_solo_coord.py
roc/film/tasks/file_handler.py
roc/film/tasks/l0_to_hk.py
roc/film/tasks/l0_to_l1_bia_current.py
roc/film/tasks/l0_to_l1_bia_sweep.py
roc/film/tasks/l0_to_l1_sbm.py
roc/film/tasks/l0_to_l1_surv.py
roc/film/tasks/make_daily_tm.py
roc/film/tasks/merge_tcreport.py
roc/film/tasks/merge_tmraw.py
roc/film/tasks/parse_dds_xml.py
roc/film/tasks/set_l0_utc.py
roc/film/tests/__init__.py
roc/film/tests/cdf_compare.py
roc/film/tests/hdf5_compare.py
roc/film/tests/test_dds_to_l0.py
roc/film/tests/test_dds_to_tc.py
roc/film/tests/test_dds_to_tm.py
roc/film/tests/test_film.py
roc/film/tests/test_l0_to_hk.py
roc/film/tests/test_l0_to_l1_bia.py
roc/film/tests/test_l0_to_l1_sbm.py
roc/film/tests/test_l0_to_l1_surv.py
roc/film/tests/test_metadata.py
roc/film/tests/tests.py
roc/film/tools/__init__.py
roc/film/tools/dataset_tasks.py
roc/film/tools/file_helpers.py
roc/film/tools/l0.py
roc/film/tools/metadata.py
roc/film/tools/skeleton.py
roc/film/tools/tools.py
roc/film/tools/xlsx2skt.py
roc_film-1.15.1.dist-info/LICENSE
roc_film-1.15.1.dist-info/METADATA
roc_film-1.15.1.dist-info/WHEEL
roc_film-1.15.1.dist-info/RECORD
